codafs/__init__.py
codafs/cfs.py
codafs/optional.py
codafs/structs.py
codafs/util.py
codafs/walk.py
codafs-0.0.0.dist-info/METADATA
codafs-0.0.0.dist-info/WHEEL
codafs-0.0.0.dist-info/entry_points.txt
codafs-0.0.0.dist-info/top_level.txt
codafs-0.0.0.dist-info/RECORD
