Metadata-Version: 2.4
Name: codafs
Version: 0.0.0
Summary: Python helpers for accessing Coda Distributed File System functionality.
Author-email: Jan Harkes <jaharkes@cs.cmu.edu>
License-Expression: LGPL-2.0
Classifier: Programming Language :: Python :: 3
Requires-Python: >=3.7
Requires-Dist: attrs
Requires-Dist: pyyaml
Provides-Extra: tqdm
Requires-Dist: tqdm; extra == "tqdm"
Provides-Extra: jsonschema
Requires-Dist: jsonschema; extra == "jsonschema"
Provides-Extra: all
Requires-Dist: jsonschema; extra == "all"
Requires-Dist: tqdm; extra == "all"
